.revision
LICENSE
MANIFEST.in
README.md
requirements.txt
setup.py
bin/archive_collectdes.py
bin/archive_esnet_snmp.py
bin/archive_lmtdb.py
bin/archive_mmperfmon.py
bin/cache_collectdes.py
bin/cache_darshan.py
bin/cache_esnet_snmp.py
bin/cache_isdct.py
bin/cache_lfsstatus.py
bin/cache_lmtdb.py
bin/cache_nersc_globuslogs.py
bin/cache_nersc_jobsdb.py
bin/cache_slurm.py
bin/cache_topology.py
bin/compare_isdct.py
bin/darshan_bad_ost.py
bin/darshan_scoreboard.py
bin/find_darshanlogs.py
bin/index_darshanlogs.py
bin/summarize_darshanlogs.py
bin/summarize_h5lmt.py
bin/summarize_job.py
bin/summarize_tts.py
examples/darshan_job_summary.ipynb
examples/lmt_missing_data.ipynb
examples/sample_summary.csv.gz
examples/tokio.analysis.umami.ipynb
examples/tokio.connectors.esnet_snmp-demo.ipynb
examples/tokio.connectors.mmperfmon-demo.ipynb
examples/tokio.connectors.nersc_isdct-demo.ipynb
examples/tokio.nersc_summary.ipynb
examples/tokio.tools.hdf5-demo.ipynb
examples/tokio.tools.hdf5-heatmap.ipynb
pytokio.egg-info/PKG-INFO
pytokio.egg-info/SOURCES.txt
pytokio.egg-info/dependency_links.txt
pytokio.egg-info/entry_points.txt
pytokio.egg-info/requires.txt
pytokio.egg-info/top_level.txt
tokio/__init__.py
tokio/common.py
tokio/config.py
tokio/debug.py
tokio/site.json
tokio/timeseries.py
tokio/analysis/__init__.py
tokio/analysis/umami.py
tokio/cli/__init__.py
tokio/cli/archive_collectdes.py
tokio/cli/archive_esnet_snmp.py
tokio/cli/archive_lmtdb.py
tokio/cli/archive_mmperfmon.py
tokio/cli/cache_collectdes.py
tokio/cli/cache_darshan.py
tokio/cli/cache_esnet_snmp.py
tokio/cli/cache_isdct.py
tokio/cli/cache_lfsstatus.py
tokio/cli/cache_lmtdb.py
tokio/cli/cache_mmperfmon.py
tokio/cli/cache_nersc_globuslogs.py
tokio/cli/cache_nersc_jobsdb.py
tokio/cli/cache_slurm.py
tokio/cli/cache_topology.py
tokio/cli/compare_isdct.py
tokio/cli/darshan_bad_ost.py
tokio/cli/darshan_scoreboard.py
tokio/cli/find_darshanlogs.py
tokio/cli/index_darshanlogs.py
tokio/cli/summarize_h5lmt.py
tokio/cli/summarize_job.py
tokio/cli/summarize_tts.py
tokio/connectors/__init__.py
tokio/connectors/_hdf5.py
tokio/connectors/cachingdb.py
tokio/connectors/collectd_es.py
tokio/connectors/common.py
